tessagon/__init__.py
tessagon/version.py
tessagon/adaptors/__init__.py
tessagon/adaptors/base_adaptor.py
tessagon/adaptors/blender_adaptor.py
tessagon/adaptors/list_adaptor.py
tessagon/adaptors/svg_adaptor.py
tessagon/adaptors/vtk_adaptor.py
tessagon/core/__init__.py
tessagon/core/abstract_tile.py
tessagon/core/alternating_tile.py
tessagon/core/grid_tile_generator.py
tessagon/core/parallelogram_tile_generator.py
tessagon/core/rotate_tile_generator.py
tessagon/core/stamp14_tessagon.py
tessagon/core/tessagon.py
tessagon/core/tessagon_discovery.py
tessagon/core/tessagon_metadata.py
tessagon/core/tile.py
tessagon/core/tile_generator.py
tessagon/core/tile_utils.py
tessagon/core/value_blend.py
tessagon/misc/__init__.py
tessagon/misc/shapes.py
tessagon/types/__init__.py
tessagon/types/big_hex_tri_tessagon.py
tessagon/types/brick_tessagon.py
tessagon/types/cloverdale_tessagon.py
tessagon/types/dissected_hex_quad_tessagon.py
tessagon/types/dissected_hex_tri_tessagon.py
tessagon/types/dissected_square_tessagon.py
tessagon/types/dissected_triangle_tessagon.py
tessagon/types/dodeca_tessagon.py
tessagon/types/dodeca_tri_tessagon.py
tessagon/types/floret_tessagon.py
tessagon/types/hex_big_tri_tessagon.py
tessagon/types/hex_square_tri_tessagon.py
tessagon/types/hex_tessagon.py
tessagon/types/hex_tri_tessagon.py
tessagon/types/islamic_hex_stars_tessagon.py
tessagon/types/islamic_stars_crosses_tessagon.py
tessagon/types/octo_tessagon.py
tessagon/types/penta2_tessagon.py
tessagon/types/penta_tessagon.py
tessagon/types/pythagorean_tessagon.py
tessagon/types/rhombus_tessagon.py
tessagon/types/square_tessagon.py
tessagon/types/square_tri2_tessagon.py
tessagon/types/square_tri_tessagon.py
tessagon/types/stanley_park_tessagon.py
tessagon/types/tri_tessagon.py
tessagon/types/valemount_tessagon.py
tessagon/types/weave_tessagon.py
tessagon/types/zig_zag_tessagon.py
tessagon-0.8.2.dist-info/LICENSE
tessagon-0.8.2.dist-info/METADATA
tessagon-0.8.2.dist-info/WHEEL
tessagon-0.8.2.dist-info/top_level.txt
tessagon-0.8.2.dist-info/RECORD
